nlp_nn/__init__.py
nlp_nn/app/__init__.py
nlp_nn/app/doc_classify/__init__.py
nlp_nn/app/doc_classify/data_set.py
nlp_nn/app/doc_classify/doc_classifier.py
nlp_nn/app/doc_classify/infer.py
nlp_nn/app/doc_classify/release.py
nlp_nn/app/doc_classify/settings.py
nlp_nn/app/doc_classify/train.py
nlp_nn/app/doc_sent_importance/__init__.py
nlp_nn/app/doc_sent_importance/data_set.py
nlp_nn/app/doc_sent_importance/doc_sent_importance.py
nlp_nn/app/doc_sent_importance/infer.py
nlp_nn/app/doc_sent_importance/release.py
nlp_nn/app/doc_sent_importance/settings.py
nlp_nn/app/doc_sent_importance/train.py
nlp_nn/app/sent_classify/__init__.py
nlp_nn/app/sent_classify/data_set.py
nlp_nn/app/sent_classify/infer.py
nlp_nn/app/sent_classify/release.py
nlp_nn/app/sent_classify/sent_classifier.py
nlp_nn/app/sent_classify/settings.py
nlp_nn/app/sent_classify/train.py
nlp_nn/app/sent_multi_classify/__init__.py
nlp_nn/app/sent_multi_classify/data_set.py
nlp_nn/app/sent_multi_classify/infer.py
nlp_nn/app/sent_multi_classify/release.py
nlp_nn/app/sent_multi_classify/sent_multi_classifier.py
nlp_nn/app/sent_multi_classify/settings.py
nlp_nn/app/sent_multi_classify/train.py
nlp_nn/app/sent_similarity/__init__.py
nlp_nn/app/sent_similarity/data_set.py
nlp_nn/app/sent_similarity/infer.py
nlp_nn/app/sent_similarity/release.py
nlp_nn/app/sent_similarity/sent_similarity.py
nlp_nn/app/sent_similarity/settings.py
nlp_nn/app/sent_similarity/train.py
nlp_nn/app/token_classify/__init__.py
nlp_nn/app/token_classify/data_set.py
nlp_nn/app/token_classify/infer.py
nlp_nn/app/token_classify/release.py
nlp_nn/app/token_classify/settings.py
nlp_nn/app/token_classify/token_classifier.py
nlp_nn/app/token_classify/train.py
nlp_nn/base/__init__.py
nlp_nn/base/abstract.py
nlp_nn/base/common.py
nlp_nn/base/layer.py
nlp_nn/base/metrics.py
nlp_nn/base/model_data.py
nlp_nn/base/model_dict.py
nlp_nn/base/tokenizer.py
nlp_nn/base/utils.py
nlp_nn-0.0.11.0.dist-info/METADATA
nlp_nn-0.0.11.0.dist-info/WHEEL
nlp_nn-0.0.11.0.dist-info/top_level.txt
nlp_nn-0.0.11.0.dist-info/RECORD
